{
  "SubTexture": [
    {
      "frameX": -3,
      "y": 1,
      "frameY": -1,
      "frameWidth": 32,
      "width": 26,
      "frameHeight": 32,
      "height": 31,
      "name": "down/1",
      "x": 1
    },
    {
      "frameX": -5,
      "y": 1,
      "frameY": -1,
      "frameWidth": 32,
      "width": 25,
      "frameHeight": 32,
      "height": 31,
      "name": "down/3",
      "x": 29
    },
    {
      "frameX": -4,
      "y": 68,
      "frameY": 0,
      "frameWidth": 32,
      "width": 25,
      "frameHeight": 32,
      "height": 32,
      "name": "down/2",
      "x": 1
    },
    {
      "frameX": -4,
      "y": 34,
      "frameY": 0,
      "frameWidth": 32,
      "width": 25,
      "frameHeight": 32,
      "height": 32,
      "name": "up/2",
      "x": 1
    },
    {
      "frameX": -4,
      "y": 34,
      "frameY": -1,
      "frameWidth": 32,
      "width": 25,
      "frameHeight": 32,
      "height": 31,
      "name": "up/1",
      "x": 28
    },
    {
      "frameX": -4,
      "y": 1,
      "frameY": -1,
      "frameWidth": 32,
      "width": 25,
      "frameHeight": 32,
      "height": 31,
      "name": "up/3",
      "x": 56
    },
    {
      "frameX": -4,
      "y": 67,
      "frameY": 0,
      "frameWidth": 32,
      "width": 22,
      "frameHeight": 32,
      "height": 32,
      "name": "left/2",
      "x": 53
    },
    {
      "frameX": -3,
      "y": 1,
      "frameY": -1,
      "frameWidth": 32,
      "width": 24,
      "frameHeight": 32,
      "height": 31,
      "name": "left/1",
      "x": 83
    },
    {
      "frameX": -4,
      "y": 34,
      "frameY": -1,
      "frameWidth": 32,
      "width": 22,
      "frameHeight": 32,
      "height": 31,
      "name": "left/3",
      "x": 79
    },
    {
      "frameX": -6,
      "y": 67,
      "frameY": 0,
      "frameWidth": 32,
      "width": 22,
      "frameHeight": 32,
      "height": 32,
      "name": "right/2",
      "x": 77
    },
    {
      "frameX": -6,
      "y": 34,
      "frameY": -1,
      "frameWidth": 32,
      "width": 22,
      "frameHeight": 32,
      "height": 31,
      "name": "right/3",
      "x": 55
    },
    {
      "frameX": -5,
      "y": 67,
      "frameY": -1,
      "frameWidth": 32,
      "width": 23,
      "frameHeight": 32,
      "height": 31,
      "name": "right/1",
      "x": 28
    }
  ],
  "width": 128,
  "height": 128,
  "name": "knight"
}